{
  "title": "ThirstyPigs",
  "date": "2024-01-26T00:00:00",
  "players": [
    {
      "name": "Josh",
      "scores": [
        0,
        0,
        0,
        0,
        0,
        0,
        0,
        0,
        0,
        0
      ]
    },
    {
      "name": "Esme",
      "scores": [
        0,
        0,
        40,
        40,
        79,
        79,
        79,
        126,
        170,
        170
      ]
    },
    {
      "name": "Dom",
      "scores": [
        0,
        0,
        18,
        50,
        69,
        69,
        69,
        95,
        95,
        95
      ]
    },
    {
      "name": "Scar",
      "scores": [
        21,
        21,
        53,
        53,
        53,
        0,
        0,
        0,
        46,
        46
      ]
    }
  ]
}
